[
    {
        "title": "Introduction to Mac and the terminal", 
        "lesson": "./terminal/mac-terminal.md"
    },
    {
        "title": "A New Terminal", 
        "lesson": "./terminal/a-new-terminal.md"
    },
    {
        "title": "History of Version Control", 
        "lesson": "./git-intro/vc-history.md"
    },
    {
        "title": "Git Set Up", 
        "lesson": "./git-intro/git-setup.md"
    },
    {
        "title": "Gitting Started", 
        "lesson": "./git-intro/gitting-started.md"
    },
    {
        "title": "Gitting Started Labs", 
        "lesson": "./git-intro/gitting-started-labs.md"
    },
    {
        "title": "GitHub", 
        "lesson": "./github-intro/intro-to-github.md"
    },
    {
        "title": "GitHub Labs", 
        "lesson": "./github-intro/github-intro-lab.md"
    },	
	{
		"title": "pycharm-setup",
		"lesson": "pycharm-setup.md"
	},	
	{
		"title": "math-operators",
		"lesson": "math-operators.md"
	},	
	{
		"title": "print-function",
		"lesson": "print-function.md"
	},	
	{
		"title": "exceptions",
		"lesson": "exceptions.md"
	},	
	{
		"title": "loops",
		"lesson": "loops.md"
	},	
	{
		"title": "data-structures",
		"lesson": "data-structures.md"
	},	
	{
		"title": "strings",
		"lesson": "strings.md"
	},	
	{
		"title": "formatting-and-input",
		"lesson": "formatting-and-input.md"
	},	
	{
		"title": "base-conversions",
		"lesson": "base-conversions.md"
	},	
	{
		"title": "comments",
		"lesson": "comments.md"
	},	
	{
		"title": "classes",
		"lesson": "classes.md"
	},	
	{
		"title": "functions",
		"lesson": "functions.md"
	},	
	{
		"title": "file-manipulation",
		"lesson": "file-manipulation.md"
	},	
	{
		"title": "math-functions",
		"lesson": "math-functions.md"
	},	
	{
		"title": "conditional-statements",
		"lesson": "conditional-statements.md"
	},	
	{
		"title": "variables",
		"lesson": "variables.md"
	},	
	{
		"title": "booleans",
		"lesson": "booleans.md"
	}
]